ncsu_courses/__init__.py
ncsu_courses/_api.py
ncsu_courses/_parsers.py
ncsu_courses/catalog.py
ncsu_courses/classes.py
ncsu_courses/datatypes.py
ncsu_courses/subjects.py
ncsu_courses/term.py
ncsu_courses-0.4.0.dist-info/LICENSE
ncsu_courses-0.4.0.dist-info/METADATA
ncsu_courses-0.4.0.dist-info/WHEEL
ncsu_courses-0.4.0.dist-info/top_level.txt
ncsu_courses-0.4.0.dist-info/RECORD
