Metadata-Version: 2.2
Name: ncsu_courses
Version: 0.4.0
Summary: A Python library for retrieving data about NCSU's course offerings and sections
Requires-Python: >=3.13
License-File: LICENSE
Requires-Dist: bs4>=0.0.2
Requires-Dist: requests>=2.32.3
